LICENSE.txt
MANIFEST.in
README.md
Readme_how_to_pip_update.txt
Readme_how_to_upload_to_PyPi.txt
setup.py
ngtsio/__init__.py
ngtsio/ngtsio.py
ngtsio/ngtsio_examples.py
ngtsio/ngtsio_find.py
ngtsio/ngtsio_get.py
ngtsio/test_ngtsio_find.py
ngtsio/test_ngtsio_get.py
ngtsio.egg-info/.DS_Store
ngtsio.egg-info/PKG-INFO
ngtsio.egg-info/SOURCES.txt
ngtsio.egg-info/dependency_links.txt
ngtsio.egg-info/top_level.txt